mdllama/__init__.py
mdllama/__main__.py
mdllama/cli.py
mdllama/colors.py
mdllama/config.py
mdllama/history.py
mdllama/input_utils.py
mdllama/main.py
mdllama/model_manager.py
mdllama/ollama_client.py
mdllama/openai_client.py
mdllama/output.py
mdllama/release.py
mdllama/session.py
mdllama/version.py
mdllama/web_search.py
mdllama-4.2.5.dist-info/licenses/LICENSE
mdllama-4.2.5.dist-info/METADATA
mdllama-4.2.5.dist-info/WHEEL
mdllama-4.2.5.dist-info/entry_points.txt
mdllama-4.2.5.dist-info/top_level.txt
mdllama-4.2.5.dist-info/RECORD
