Metadata-Version: 2.4
Name: mdllama
Version: 4.2.5
Summary: A command-line interface for Ollama API
Author: QinCai-rui
License-Expression: GPL-3.0-only
Requires-Python: >=3.7
License-File: LICENSE
Requires-Dist: requests
Requires-Dist: ollama
Requires-Dist: colorama
Requires-Dist: rich
Dynamic: license-file
Dynamic: requires-python
